{"hash":"2c88c5a1499fdeb77b1ba37442da3956da864c22","data":{"storyblokEntry":{"id":"story-13274746-de","full_slug":"de/gala","content":{"_uid":"fc930134-ac24-40f9-85df-29b88a6b6760","body":[{"_uid":"cb3125a8-8706-41e9-a1ff-c39d347b8912","image":{"url":"//a.storyblok.com/f/84097/2777x1852/62925104d0/gala-cover.jpg","filename":"gala-cover.jpg","path":"storyblok_images/gala-cover.jpg"},"title":"Gala","component":"project_header","description":{"type":"doc","content":[{"type":"paragraph","content":[{"text":"Modernes User Interface und neue Funktionen für Android und iOS.","type":"text"}]}]},"_editable":"<!--#storyblok#{\"name\": \"project_header\", \"space\": \"84097\", \"uid\": \"cb3125a8-8706-41e9-a1ff-c39d347b8912\", \"id\": \"13274746\"}-->"},{"_uid":"c5a7ddb6-b478-422a-b6c2-3af76e95434d","image":{"url":"//a.storyblok.com/f/84097/1496x970/84d08b9e62/gala-android.png","filename":"gala-android.png","path":"storyblok_images/gala-android.png"},"video":{"id":null,"alt":null,"name":"","focus":null,"title":null,"filename":"","copyright":null,"fieldtype":"asset"},"reverse":false,"headline":"Produkt Design","component":"showcase","description":{"type":"doc","content":[{"type":"paragraph","content":[{"text":"Aktuelle News über Stars und Royals, Bildergalerien und Starportraits – bestehende Funktionen wurden optimiert und Neue entwickelt. In einem neuen Look für iOS und Android.","type":"text"}]}]},"split_equally":false,"_editable":"<!--#storyblok#{\"name\": \"showcase\", \"space\": \"84097\", \"uid\": \"c5a7ddb6-b478-422a-b6c2-3af76e95434d\", \"id\": \"13274746\"}-->"},{"_uid":"8eda7bcd-8d7d-41bf-b085-77a63720adce","image":{"url":"//a.storyblok.com/f/84097/2040x1270/d7e6f6a7e6/gala-tablet.jpg","filename":"gala-tablet.jpg","path":"storyblok_images/gala-tablet.jpg"},"video":{"id":null,"alt":null,"name":"","focus":null,"title":null,"filename":"","copyright":null,"fieldtype":"asset"},"reverse":true,"headline":"Responsive Design","component":"showcase","description":{"type":"doc","content":[{"type":"paragraph","content":[{"text":"Die App ist für Smartphones und Tablets optimiert, und wurde nach dem Mobile-First Ansatz konzipiert und gestaltet.","type":"text"}]}]},"split_equally":false,"_editable":"<!--#storyblok#{\"name\": \"showcase\", \"space\": \"84097\", \"uid\": \"8eda7bcd-8d7d-41bf-b085-77a63720adce\", \"id\": \"13274746\"}-->"},{"_uid":"10e08ef6-4033-431b-b30e-e0468e7dd738","image1":{"url":"//a.storyblok.com/f/84097/1496x1000/75708e734b/gala-farben-und-schriften.png","filename":"gala-farben-und-schriften.png","path":"storyblok_images/gala-farben-und-schriften.png"},"image2":{"url":"//a.storyblok.com/f/84097/1496x1000/944e8dc123/gala-konzept.jpg","filename":"gala-konzept.jpg","path":"storyblok_images/gala-konzept.jpg"},"component":"dual_showcase","description1":{"type":"doc","content":[{"type":"paragraph","content":[{"text":"Ein neuer Schriftmix und eine angepasste Farbwelt sorgen für einen modernen und konsistenten Look.","type":"text"}]}]},"description2":{"type":"doc","content":[{"type":"paragraph","content":[{"text":"Neben der UX-Konzeption und Gestaltung der Layouts wurde das Entwicklungs-Team durch Austausch in der Planung sowie durch Pairings und Design-Reviews unterstützt.","type":"text"}]}]},"_editable":"<!--#storyblok#{\"name\": \"dual_showcase\", \"space\": \"84097\", \"uid\": \"10e08ef6-4033-431b-b30e-e0468e7dd738\", \"id\": \"13274746\"}-->"}],"component":"project","_editable":"<!--#storyblok#{\"name\": \"project\", \"space\": \"84097\", \"uid\": \"fc930134-ac24-40f9-85df-29b88a6b6760\", \"id\": \"13274746\"}-->"}},"next":{"id":"story-13274423-de","full_slug":"de/eventim","content":{"_uid":"c565b688-fbcb-40cd-ba2b-4fa2241e9e3a","body":[{"_uid":"7c20665a-92e7-4875-95db-394ed0d3c6c2","image":{"url":"//a.storyblok.com/f/84097/2554x1703/eb16edbc13/eventim-light.jpg","filename":"eventim-light.jpg","path":"storyblok_images/eventim-light.jpg"},"title":"Eventim","component":"project_header","description":{"type":"doc","content":[{"type":"paragraph","content":[{"text":"Neue visuelle Sprache und überarbeitetes UI und UX Konzept für eine Webapp zur Organisation von Veranstaltungen.","type":"text"}]}]},"_editable":"<!--#storyblok#{\"name\": \"project_header\", \"space\": \"84097\", \"uid\": \"7c20665a-92e7-4875-95db-394ed0d3c6c2\", \"id\": \"13274423\"}-->"},{"_uid":"84ac7a8d-5e52-4879-a167-58bcb450ff20","quote":{"type":"doc","content":[{"type":"paragraph","content":[{"text":"„Neben gut durchdachten Designkonzepten, hat Lennart uns stets mit neuen Blickwinkel, up-to-date Designinput und viel Freude geholfen unser Produkt weiter zu entwickeln und zu wachsen.“","type":"text"}]}]},"author":"Katharina Wulff, Senior Product Manager EVENTIM.Light","component":"quote","_editable":"<!--#storyblok#{\"name\": \"quote\", \"space\": \"84097\", \"uid\": \"84ac7a8d-5e52-4879-a167-58bcb450ff20\", \"id\": \"13274423\"}-->"},{"_uid":"fda85ead-fead-4213-ab53-bde2bf1a68a2","image":{"url":"//a.storyblok.com/f/84097/3060x1905/f66a4d69f5/eventim-light-dashboard-3x.jpg","filename":"eventim-light-dashboard-3x.jpg","path":"storyblok_images/eventim-light-dashboard-3x.jpg"},"video":{"id":null,"alt":null,"name":"","focus":null,"title":null,"filename":null,"copyright":null,"fieldtype":"asset"},"reverse":false,"headline":"Produkt Design","component":"showcase","description":{"type":"doc","content":[{"type":"paragraph","content":[{"text":"Von der Anlage des Events über Einlassstatistiken bis zur Shopkonfiguration und Abrechnung – bestehende Funktionen wurden optimiert und neue entwickelt. Alle Bereiche sind immer verfügbar, egal ob mit dem Smartphone oder am PC.","type":"text"}]}]},"split_equally":false,"_editable":"<!--#storyblok#{\"name\": \"showcase\", \"space\": \"84097\", \"uid\": \"fda85ead-fead-4213-ab53-bde2bf1a68a2\", \"id\": \"13274423\"}-->"},{"_uid":"d126b89e-0962-4905-8159-1db985509e81","image":{"url":"//a.storyblok.com/f/84097/3060x1905/4180277504/eventim-light-sales-client-3x.jpg","filename":"eventim-light-sales-client-3x.jpg","path":"storyblok_images/eventim-light-sales-client-3x.jpg"},"video":{"id":null,"alt":null,"name":"","focus":null,"title":null,"filename":null,"copyright":null,"fieldtype":"asset"},"reverse":true,"headline":"Sales Client","component":"showcase","description":{"type":"doc","content":[{"type":"paragraph","content":[{"text":"Mit der Progressive Web App können Veranstalter im Ticketbüro und direkt auf der Veranstaltung Karten verkaufen – optimiert für Tablets und Smartphones.","type":"text"}]}]},"split_equally":false,"_editable":"<!--#storyblok#{\"name\": \"showcase\", \"space\": \"84097\", \"uid\": \"d126b89e-0962-4905-8159-1db985509e81\", \"id\": \"13274423\"}-->"},{"_uid":"9d8b81bb-9c6e-4020-bc82-b1eac3c6984e","image":{"url":"//a.storyblok.com/f/84097/3060x1905/ad92dc171e/eventim-light-responsive-shop-3x.jpg","filename":"eventim-light-responsive-shop-3x.jpg","path":"storyblok_images/eventim-light-responsive-shop-3x.jpg"},"video":{"id":null,"alt":null,"name":"","focus":null,"title":null,"filename":null,"copyright":null,"fieldtype":"asset"},"reverse":false,"headline":"Invidueller Shop","component":"showcase","description":{"type":"doc","content":[{"type":"paragraph","content":[{"text":"Ich habe einen responsiven Onlineshop konzipiert und gestaltet, welcher sich einfach anpassen lässt. Auf nur einer Seite kann die Bestellung direkt im Warenkorb gesendet werden. Kunden müssen auch keine Passwörter mehr merken – falls ein Ticket verloren geht, reicht die E-Mail mit einem Magic Link.","type":"text"}]}]},"split_equally":false,"_editable":"<!--#storyblok#{\"name\": \"showcase\", \"space\": \"84097\", \"uid\": \"9d8b81bb-9c6e-4020-bc82-b1eac3c6984e\", \"id\": \"13274423\"}-->"},{"_uid":"93ac0203-ab23-4fa5-91b3-f9c891c01470","image":{"url":"//a.storyblok.com/f/84097/2244x2244/d7728a2bfe/eventim-light-concept-3x.jpg","filename":"eventim-light-concept-3x.jpg","path":"storyblok_images/eventim-light-concept-3x.jpg"},"video":{"id":null,"alt":null,"name":"","focus":null,"title":null,"filename":null,"copyright":null,"fieldtype":"asset"},"reverse":true,"headline":"UX und UI Design","component":"showcase","description":{"type":"doc","content":[{"type":"paragraph","content":[{"text":"Gemeinsam mit dem Produktteam werden neue Funktionen konzipiert. Mit Prototypen in Nutzertests werden diese vertestet und anschließend für die EntwicklerInnen aufbereitet und in Design-Reviews finalisiert.","type":"text"}]}]},"split_equally":true,"_editable":"<!--#storyblok#{\"name\": \"showcase\", \"space\": \"84097\", \"uid\": \"93ac0203-ab23-4fa5-91b3-f9c891c01470\", \"id\": \"13274423\"}-->"}],"component":"project","_editable":"<!--#storyblok#{\"name\": \"project\", \"space\": \"84097\", \"uid\": \"c565b688-fbcb-40cd-ba2b-4fa2241e9e3a\", \"id\": \"13274423\"}-->"}}},"context":{"id":"story-13274746-de","nextId":"story-13274423-de"}}